start_cloudflare/__init__.py
start_cloudflare/main.py
start_cloudflare-0.0.7.dist-info/METADATA
start_cloudflare-0.0.7.dist-info/WHEEL
start_cloudflare-0.0.7.dist-info/top_level.txt
start_cloudflare-0.0.7.dist-info/RECORD
