Metadata-Version: 2.4
Name: start-cloudflare
Version: 0.0.7
Summary: A Pydantic BaseSettings class intended to be extended by other Cloudflare services.
Requires-Python: >=3.13
Requires-Dist: python-dotenv>=1.0
Requires-Dist: pydantic-settings>=2.10.1
Requires-Dist: pydantic>=2.11.9
Requires-Dist: email-validator>=2.3.0
